langcrew_tools/__init__.py
langcrew_tools/base.py
langcrew_tools/browser/README.md
langcrew_tools/browser/__init__.py
langcrew_tools/browser/browser_manager.py
langcrew_tools/browser/browser_use_patches.py
langcrew_tools/browser/browser_use_streaming_tool.py
langcrew_tools/browser/prompt.py
langcrew_tools/browser/sandbox_config.py
langcrew_tools/browser/langchain/__init__.py
langcrew_tools/browser/langchain/chat.py
langcrew_tools/browser/langchain/serializer.py
langcrew_tools/cloud_phone/README.md
langcrew_tools/cloud_phone/__init__.py
langcrew_tools/cloud_phone/agent_as_tool.py
langcrew_tools/cloud_phone/context.py
langcrew_tools/cloud_phone/langchain_tools.py
langcrew_tools/cloud_phone/virtual_phone_hook.py
langcrew_tools/cloud_phone/init_configs/droidrun_config.xml
langcrew_tools/code_interpreter/README.md
langcrew_tools/code_interpreter/__init__.py
langcrew_tools/code_interpreter/langchain_tools.py
langcrew_tools/commands/README.md
langcrew_tools/commands/__init__.py
langcrew_tools/commands/langchain_tools.py
langcrew_tools/commands/terminal_formatter.py
langcrew_tools/delivery/README.md
langcrew_tools/delivery/__init__.py
langcrew_tools/delivery/langchain_tools.py
langcrew_tools/fetch/README.md
langcrew_tools/fetch/__init__.py
langcrew_tools/fetch/langchain_tools.py
langcrew_tools/filesystem/README.md
langcrew_tools/filesystem/__init__.py
langcrew_tools/filesystem/file_validators.py
langcrew_tools/filesystem/langchain_tools.py
langcrew_tools/hitl/README.md
langcrew_tools/hitl/__init__.py
langcrew_tools/hitl/langchain_tools.py
langcrew_tools/image_gen/README.md
langcrew_tools/image_gen/__init__.py
langcrew_tools/image_gen/langchain_tools.py
langcrew_tools/image_parser/README.md
langcrew_tools/image_parser/__init__.py
langcrew_tools/image_parser/config.py
langcrew_tools/image_parser/langchain_tools.py
langcrew_tools/plan/README.md
langcrew_tools/plan/__init__.py
langcrew_tools/plan/langchain_tool.py
langcrew_tools/search/README.md
langcrew_tools-0.1.1.dist-info/METADATA
langcrew_tools-0.1.1.dist-info/WHEEL
langcrew_tools-0.1.1.dist-info/licenses/LICENSE
langcrew_tools-0.1.1.dist-info/RECORD
