Metadata-Version: 2.4
Name: langcrew-tools
Version: 0.1.1
Summary: Tool collection for LangCrew - Building multi-agent applications
Project-URL: Homepage, https://langcrew.ai/
Project-URL: Repository, https://github.com/01-ai/langcrew
Project-URL: Documentation, https://langcrew.ai/guides/tools/
Project-URL: Issues, https://github.com/01-ai/langcrew/issues
Author-email: BTM Team <btm@langcrew.ai>
License-Expression: MIT
License-File: LICENSE
Keywords: agents,ai,langchain,llm,multi-agent,orchestration,tools
Classifier: Development Status :: 3 - Alpha
Classifier: Intended Audience :: Developers
Classifier: License :: OSI Approved :: MIT License
Classifier: Programming Language :: Python :: 3
Classifier: Programming Language :: Python :: 3.10
Classifier: Programming Language :: Python :: 3.11
Classifier: Programming Language :: Python :: 3.12
Requires-Python: <3.13,>=3.10
Requires-Dist: agentbox-python-sdk>=0.2.9
Requires-Dist: aiobotocore>=2.23.1
Requires-Dist: aiohttp>=3.12.15
Requires-Dist: beautifulsoup4>=4.13.5
Requires-Dist: browser-use==0.5.5; python_version >= '3.11'
Requires-Dist: httpx>=0.28.1
Requires-Dist: langchain-core>=0.3.72
Requires-Dist: langchain-text-splitters>=0.3.9
Requires-Dist: langchain>=0.3.27
Requires-Dist: langcrew>=0.1.0
Requires-Dist: langgraph>=0.6.0
Requires-Dist: langmem
Requires-Dist: playwright==1.54.0
Requires-Dist: pydantic>=2.7.4
Requires-Dist: pytest-dotenv>=0.5.2
Requires-Dist: requests>=2.32.4
Requires-Dist: sqlalchemy>=2.0.42
Requires-Dist: volcengine-python-sdk[ark]>=4.0.11
Provides-Extra: all
Requires-Dist: codespell; extra == 'all'
Requires-Dist: mypy>=1.0.0; extra == 'all'
Requires-Dist: pytest-asyncio>=0.21.0; extra == 'all'
Requires-Dist: pytest-cov; extra == 'all'
Requires-Dist: pytest-dotenv>=0.5.0; extra == 'all'
Requires-Dist: pytest-mock>=3.10.0; extra == 'all'
Requires-Dist: pytest-watcher; extra == 'all'
Requires-Dist: pytest-xdist[psutil]; extra == 'all'
Requires-Dist: pytest>=7.0.0; extra == 'all'
Requires-Dist: ruff>=0.1.0; extra == 'all'
Requires-Dist: types-requests>=2.31.0; extra == 'all'
Provides-Extra: development
Requires-Dist: codespell; extra == 'development'
Requires-Dist: mypy>=1.0.0; extra == 'development'
Requires-Dist: pytest-watcher; extra == 'development'
Requires-Dist: ruff>=0.1.0; extra == 'development'
Requires-Dist: types-requests>=2.31.0; extra == 'development'
Provides-Extra: testing
Requires-Dist: pytest-asyncio>=0.21.0; extra == 'testing'
Requires-Dist: pytest-cov; extra == 'testing'
Requires-Dist: pytest-dotenv>=0.5.0; extra == 'testing'
Requires-Dist: pytest-mock>=3.10.0; extra == 'testing'
Requires-Dist: pytest-xdist[psutil]; extra == 'testing'
Requires-Dist: pytest>=7.0.0; extra == 'testing'
